spacy_biaffine_parser-0.1.0.dist-info/RECORD
spacy_biaffine_parser-0.1.0.dist-info/LICENSE
spacy_biaffine_parser-0.1.0.dist-info/WHEEL
spacy_biaffine_parser-0.1.0.dist-info/entry_points.txt
spacy_biaffine_parser-0.1.0.dist-info/top_level.txt
spacy_biaffine_parser-0.1.0.dist-info/METADATA
spacy_biaffine_parser/with_splits.py
spacy_biaffine_parser/mst.pyx
spacy_biaffine_parser/with_minibatch_by_padded_size.py
spacy_biaffine_parser/arc_predicter.pyx
spacy_biaffine_parser/bilinear.py
spacy_biaffine_parser/__init__.py
spacy_biaffine_parser/with_pad_seq_unpad_matrix.py
spacy_biaffine_parser/_util.py
spacy_biaffine_parser/arc_labeler.cpython-39-darwin.so
spacy_biaffine_parser/mst.pyi
spacy_biaffine_parser/arc_labeler.pyx
spacy_biaffine_parser/pytorch_pairwise_bilinear.py
spacy_biaffine_parser/pairwise_bilinear.py
spacy_biaffine_parser/mst.pxd
spacy_biaffine_parser/mst.cpython-39-darwin.so
spacy_biaffine_parser/arc_predicter.cpython-39-darwin.so
spacy_biaffine_parser/pytorch_bilinear.py
spacy_biaffine_parser/tests/test_pytorch_bilinear.py
spacy_biaffine_parser/tests/test_with_pad_seq_unpad_matrix.py
spacy_biaffine_parser/tests/util.py
spacy_biaffine_parser/tests/test_arc_labeler.py
spacy_biaffine_parser/tests/test_with_splits.py
spacy_biaffine_parser/tests/test_arc_predicter.py
spacy_biaffine_parser/tests/__init__.py
spacy_biaffine_parser/tests/test_with_minibatch_by_padded_size.py
spacy_biaffine_parser/tests/test_mst.py
