Metadata-Version: 2.1
Name: spacy-biaffine-parser
Version: 0.1.0
Summary: Biaffine dependency parser for spaCy
Home-page: https://github.com/explosion/spacy-biaffine-parser
Author: Explosion
Author-email: contact@explosion.ai
License: MIT
Requires-Python: >=3.9
License-File: LICENSE
Requires-Dist: spacy <4.1.0,>=4.0.0.dev1
Requires-Dist: torch >=1.5.0
